kiss_ai_stack/__init__.py
kiss_ai_stack/core/__init__.py
kiss_ai_stack/core/ai_clients/__init__.py
kiss_ai_stack/core/ai_clients/ai_client_abc.py
kiss_ai_stack/core/ai_clients/ai_client_factory.py
kiss_ai_stack/core/ai_clients/vendors/__init__.py
kiss_ai_stack/core/ai_clients/vendors/openai_client.py
kiss_ai_stack/core/config/__init__.py
kiss_ai_stack/core/config/ondemand_packages.py
kiss_ai_stack/core/config/stack_properties.py
kiss_ai_stack/core/config/stack_validator.py
kiss_ai_stack/core/dbs/__init__.py
kiss_ai_stack/core/dbs/db_abc.py
kiss_ai_stack/core/dbs/db_factory.py
kiss_ai_stack/core/dbs/vendors/__init__.py
kiss_ai_stack/core/dbs/vendors/chroma_db.py
kiss_ai_stack/core/models/__init__.py
kiss_ai_stack/core/models/config/__init__.py
kiss_ai_stack/core/models/config/ai_client_props.py
kiss_ai_stack/core/models/config/stack_props.py
kiss_ai_stack/core/models/config/tool_props.py
kiss_ai_stack/core/models/config/vdb_props.py
kiss_ai_stack/core/models/core/__init__.py
kiss_ai_stack/core/models/core/query_classification_response.py
kiss_ai_stack/core/models/core/rag_response.py
kiss_ai_stack/core/models/enums/__init__.py
kiss_ai_stack/core/models/enums/ai_client_vendor.py
kiss_ai_stack/core/models/enums/db_kind.py
kiss_ai_stack/core/models/enums/db_vendor.py
kiss_ai_stack/core/models/enums/tool_kind.py
kiss_ai_stack/core/stack/__init__.py
kiss_ai_stack/core/stack/stack.py
kiss_ai_stack/core/stack/stacks.py
kiss_ai_stack/core/tools/__init__.py
kiss_ai_stack/core/tools/tool.py
kiss_ai_stack/core/tools/tool_builder.py
kiss_ai_stack/core/utilities/__init__.py
kiss_ai_stack/core/utilities/document_utils.py
kiss_ai_stack/core/utilities/install_package.py
kiss_ai_stack/core/utilities/logger.py
kiss_ai_stack/core/utilities/yaml_reader.py
kiss_ai_stack_core-0.1.0a28.dist-info/LICENSE
kiss_ai_stack_core-0.1.0a28.dist-info/METADATA
kiss_ai_stack_core-0.1.0a28.dist-info/WHEEL
kiss_ai_stack_core-0.1.0a28.dist-info/top_level.txt
kiss_ai_stack_core-0.1.0a28.dist-info/RECORD
