Metadata-Version: 2.1
Name: kiss-ai-stack-core
Version: 0.1.0a28
Summary: KISS AI Stack's RAG builder core
Author: KISS AI Stack, Lahiru Pathirage
License: MIT
Project-URL: Homepage, https://github.com/kiss-ai-stack
Project-URL: Repository, https://github.com/kiss-ai-stack
Project-URL: Documentation, https://github.com/kiss-ai-stack/kiss-ai-stack-core/main/README.md
Keywords: ai,stack,rag,prompt,yaml,machine-learning,llm,document-processing
Classifier: Development Status :: 3 - Alpha
Classifier: Intended Audience :: Developers
Classifier: License :: OSI Approved :: MIT License
Classifier: Programming Language :: Python :: 3.12
Classifier: Topic :: Scientific/Engineering :: Artificial Intelligence
Requires-Python: >=3.12
License-File: LICENSE
Requires-Dist: asyncio~=3.4.3
Requires-Dist: aiofiles~=24.1.0
Requires-Dist: PyYAML~=6.0.2
Requires-Dist: pydantic~=2.10.1
Requires-Dist: unstructured~=0.16.8
Requires-Dist: tiktoken~=0.8.0
Requires-Dist: tokenizers~=0.20.3
Requires-Dist: pandas~=2.2.3
Requires-Dist: numpy~=1.26.4
Requires-Dist: unstructured[xlsx]~=0.16.8
Requires-Dist: unstructured[pdf]~=0.16.8
Requires-Dist: unstructured[docx]~=0.16.8
Requires-Dist: unstructured[csv]~=0.16.8
